Workbook

Sheet Sources
A1: ANALYSE FINANCIERE - CAPGEMINI SE
A2: Exercices 2022 - 2023 - 2024 (comptes consolides IFRS, en millions d'euros)
A4: Societe analysee | B4: Capgemini SE - societe europeenne, secteur conseil / services IT, cotee sur Euronext Paris (CAP)
A5: Devise | B5: Millions d'euros (M EUR), sauf indication contraire
A6: Referentiel comptable | B6: IFRS tel qu'adopte par l'Union europeenne
A8: Document / donnee | B8: Lien source
A9: Compte de resultat consolide 2023-2024 | B9: https://investors.capgemini.com/file/11729?download=1 (Etats financiers consolides au 31/12/2024, section 5.2.1)
A10: Etat consolide de la situation financiere 2023-2024 | B10: https://investors.capgemini.com/file/11729?download=1 (section 5.2.3)
A11: Tableau des flux de tresorerie consolides 2023-2024 | B11: https://investors.capgemini.com/file/11729?download=1 (section 5.2.4)
A12: Endettement net 2023-2024 | B12: https://investors.capgemini.com/file/11729?download=1 (Note 22)
A13: Compte de resultat consolide 2022 (comparatif 2021) | B13: https://investors.capgemini.com/fr/file/19316?download=1 (page 9)
A14: Etat de la situation financiere 2022 (comparatif 2021) | B14: https://investors.capgemini.com/fr/file/19316?download=1 (page 11)
A15: Tableau de flux de tresorerie 2022 | B15: https://investors.capgemini.com/fr/file/19316?download=1 (page 12)
A16: Endettement net 2022 / Principales donnees financieres 2018-2022 | B16: https://investors.capgemini.com/fr/file/19316?download=1 (page 3, Note 22)
A18: Limites et hypotheses
A19: - Les chiffres proviennent des comptes CONSOLIDES du groupe Capgemini (perimetre mondial), pas des seuls comptes sociaux de Capgemini SE.
A20: - Tous les montants sont arrondis au million d'euros le plus proche, tels que publies par la societe.
A21: - Cette analyse est construite a des fins d'entrainement / illustration methodologique et ne constitue pas un conseil d'investissement.

Sheet Synthese
A1: SYNTHESE - CAPGEMINI SE (2022-2024)
A3: Indicateur cle | B3: 2022 | C3: 2023 | D3: 2024
A4: Chiffre d'affaires (M EUR) | B4: ='Compte de resultat'!B5 -> 21995 | C4: ='Compte de resultat'!C5 -> 22522 | D4: ='Compte de resultat'!D5 -> 22096
A5: Marge operationnelle (M EUR) | B5: ='Compte de resultat'!B10 -> 2867 | C5: ='Compte de resultat'!C10 -> 2991 | D5: ='Compte de resultat'!D10 -> 2934
A6: Resultat net part du Groupe (M EUR) | B6: ='Compte de resultat'!B17 -> 1547 | C6: ='Compte de resultat'!C17 -> 1663 | D6: ='Compte de resultat'!D17 -> 1671
A7: Marge operationnelle (%) | B7: ='Ratios financiers'!B6 -> 0.13034781 | C7: ='Ratios financiers'!C6 -> 0.13280348 | D7: ='Ratios financiers'!D6 -> 0.13278421
A8: Marge nette (%) | B8: ='Ratios financiers'!B7 -> 0.070470561 | C8: ='Ratios financiers'!C7 -> 0.074060918 | D8: ='Ratios financiers'!D7 -> 0.07589609
A9: ROE part Groupe (%) | B9: ='Ratios financiers'!B8 -> 0.15904184 | C9: ='Ratios financiers'!C8 -> 0.15907786 | D9: ='Ratios financiers'!D8 -> 0.14191083
A10: Endettement net (M EUR) | B10: ='Flux de tresorerie'!B14 -> 2566 | C10: ='Flux de tresorerie'!C14 -> 2047 | D10: ='Flux de tresorerie'!D14 -> 2107
A11: Endettement net / EBITDA | B11: ='Ratios financiers'!B14 -> 0.71556051 | C11: ='Ratios financiers'!C14 -> 0.55459225 | D11: ='Ratios financiers'!D14 -> 0.58252696
A12: Ratio de liquidite generale | B12: ='Ratios financiers'!B18 -> 1.2823311 | C12: ='Ratios financiers'!C18 -> 1.3441854 | D12: ='Ratios financiers'!D18 -> 1.2074199
A13: Autonomie financiere (%) | B13: ='Ratios financiers'!B12 -> 0.38239334 | C13: ='Ratios financiers'!C12 -> 0.4240081 | D13: ='Ratios financiers'!D12 -> 0.45974279
A14: DSO - delai clients (jours) | B14: ='Ratios financiers'!B22 -> 14.53694 | C14: ='Ratios financiers'!C22 -> 12.770624 | D14: ='Ratios financiers'!D22 -> 12.471714
A17: Tableau de bord alimente par formules depuis les feuilles Compte de resultat / Bilan / Flux de tresorerie / Ratios financiers.

Sheet Compte de resultat
A1: COMPTE DE RESULTAT CONSOLIDÉ
A2: En millions d'euros
A4: Rubrique | B4: 2022 | C4: 2023 | D4: 2024 | E4: Var. 23/22 | F4: Var. 24/23
A5: Chiffre d'affaires | B5: 21995 | C5: 22522 | D5: 22096 | E5: =IFERROR(C5/B5-1,"-") -> 0.023959991 | F5: =IFERROR(D5/C5-1,"-") -> -0.018914839
A6: Couts des services rendus | B6: -16163 | C6: -16474 | D6: -16044 | E6: =IFERROR(C6/B6-1,"-") -> 0.019241477 | F6: =IFERROR(D6/C6-1,"-") -> -0.026101736
A7: Frais commerciaux | B7: -1518 | C7: -1598 | D7: -1634 | E7: =IFERROR(C7/B7-1,"-") -> 0.052700922 | F7: =IFERROR(D7/C7-1,"-") -> 0.02252816
A8: Frais generaux et administratifs | B8: -1447 | C8: -1459 | D8: -1484 | E8: =IFERROR(C8/B8-1,"-") -> 0.00829302 | F8: =IFERROR(D8/C8-1,"-") -> 0.017135024
A9: Charges operationnelles | B9: -19128 | C9: -19531 | D9: -19162 | E9: =IFERROR(C9/B9-1,"-") -> 0.021068591 | F9: =IFERROR(D9/C9-1,"-") -> -0.018893042
A10: Marge operationnelle | B10: 2867 | C10: 2991 | D10: 2934 | E10: =IFERROR(C10/B10-1,"-") -> 0.043250785 | F10: =IFERROR(D10/C10-1,"-") -> -0.019057172
A11: Autres produits et charges operationnels | B11: -474 | C11: -645 | D11: -578 | E11: =IFERROR(C11/B11-1,"-") -> 0.36075949 | F11: =IFERROR(D11/C11-1,"-") -> -0.10387597
A12: Resultat d'exploitation | B12: 2393 | C12: 2346 | D12: 2356 | E12: =IFERROR(C12/B12-1,"-") -> -0.019640618 | F12: =IFERROR(D12/C12-1,"-") -> 0.0042625746
A13: Resultat financier net | B13: -129 | C13: -42 | D13: 13 | E13: =IFERROR(C13/B13-1,"-") -> -0.6744186 | F13: =IFERROR(D13/C13-1,"-") -> -1.3095238
A14: Charge d'impot | B14: -710 | C14: -626 | D14: -681 | E14: =IFERROR(C14/B14-1,"-") -> -0.11830986 | F14: =IFERROR(D14/C14-1,"-") -> 0.087859425
A15: Resultat des entreprises associees | B15: -4 | C15: -10 | D15: -11 | E15: =IFERROR(C15/B15-1,"-") -> 1.5 | F15: =IFERROR(D15/C15-1,"-") -> 0.1
A16: RESULTAT NET | B16: 1550 | C16: 1668 | D16: 1677 | E16: =IFERROR(C16/B16-1,"-") -> 0.076129032 | F16: =IFERROR(D16/C16-1,"-") -> 0.0053956835
... A18: dont interets minoritaires | B18: 3 | C18: 5 | D18: 6 | E18: =IFERROR(C18/B18-1,"-") -> 0.66666667 | F18: =IFERROR(D18/C18-1,"-") -> 0.2
A21: % DU CHIFFRE D'AFFAIRES
A22: Rubrique | B22: 2022 | C22: 2023 | D22: 2024
A23: Marge operationnelle | B23: =B10/$B$5 -> 0.13034781 | C23: =C10/$C$5 -> 0.13280348 | D23: =D10/$D$5 -> 0.13278421
A24: Resultat d'exploitation | B24: =B12/$B$5 -> 0.10879745 | C24: =C12/$C$5 -> 0.10416482 | D24: =D12/$D$5 -> 0.10662563
A25: RESULTAT NET | B25: =B16/$B$5 -> 0.070470561 | C25: =C16/$C$5 -> 0.074060918 | D25: =D16/$D$5 -> 0.07589609

Sheet Bilan
A1: BILAN CONSOLIDE (ETAT DE LA SITUATION FINANCIERE)
A2: En millions d'euros, au 31 decembre
A4: ACTIF | B4: 2022 | C4: 2023 | D4: 2024 | E4: Var. 23/22 | F4: Var. 24/23
A5: Ecarts d'acquisition (goodwill) | B5: 11090 | C5: 11213 | D5: 12343 | E5: =IFERROR(C5/B5-1,'-') -> 0.011091073 | F5: =IFERROR(D5/C5-1,"-") -> 0.10077589
A6: Immobilisations incorporelles | B6: 906 | C6: 798 | D6: 837 | E6: =IFERROR(C6/B6-1,"-") -> -0.1192053 | F6: =IFERROR(D6/C6-1,"-") -> 0.04887218
A7: Immobilisations corporelles | B7: 876 | C7: 788 | D7: 755 | E7: =IFERROR(C7/B7-1,"-") -> -0.10045662 | F7: =IFERROR(D7/C7-1,"-") -> -0.041878173
A8: Droits d'utilisation (contrats de location) | B8: 721 | C8: 783 | D8: 862 | E8: =IFERROR(C8/B8-1,"-") -> 0.085991678 | F8: =IFERROR(D8/C8-1,"-") -> 0.100894
A9: Impots differes actifs | B9: 708 | C9: 560 | D9: 579 | E9: =IFERROR(C9/B9-1,"-") -> -0.20903955 | F9: =IFERROR(D9/C9-1,"-") -> 0.033928571
A10: Autres actifs non courants | B10: 836 | C10: 814 | D10: 976 | E10: =IFERROR(C10/B10-1,"-") -> -0.026315789 | F10: =IFERROR(D10/C10-1,"-") -> 0.1990172
A11: TOTAL ACTIF NON COURANT | B11: 15137 | C11: 14956 | D11: 16352 | E11: =IFERROR(C11/B11-1,"-") -> -0.011957455 | F11: =IFERROR(D11/C11-1,"-") -> 0.093340465
A12: Couts des contrats | B12: 140 | C12: 132 | D12: 143 | E12: =IFERROR(C12/B12-1,"-") -> -0.057142857 | F12: =IFERROR(D12/C12-1,"-") -> 0.083333333
A13: Actifs sur contrats | B13: 1784 | C13: 1670 | D13: 1838 | E13: =IFERROR(C13/B13-1,"-") -> -0.063901345 | F13: =IFERROR(D13/C13-1,"-") -> 0.1005988
A14: Creances clients | B14: 3329 | C14: 3286 | D14: 3238 | E14: =IFERROR(C14/B14-1,"-") -> -0.012916792 | F14: =IFERROR(D14/C14-1,"-") -> -0.014607425
A15: Creances d'impot courantes | B15: 106 | C15: 148 | D15: 169 | E15: =IFERROR(C15/B15-1,"-") -> 0.39622642 | F15: =IFERROR(D15/C15-1,"-") -> 0.14189189
A16: Autres actifs courants | B16: 795 | C16: 811 | D16: 863 | E16: =IFERROR(C16/B16-1,"-") -> 0.020125786 | F16: =IFERROR(D16/C16-1,"-") -> 0.064118372
A17: Actifs de gestion de tresorerie | B17: 386 | C17: 161 | D17: 268 | E17: =IFERROR(C17/B17-1,"-") -> -0.58290155 | F17: =IFERROR(D17/C17-1,"-") -> 0.66459627
... A20: TOTAL ACTIF | B20: 25479 | C20: 24700 | D20: 25660 | E20: =IFERROR(C20/B20-1,"-") -> -0.030574198 | F20: =IFERROR(D20/C20-1,"-") -> 0.038866397
A22: PASSIF (CAPITAUX PROPRES ET DETTES) | B22: 2022 | C22: 2023 | D22: 2024 | E22: Var. 23/22 | F22: Var. 24/23
A23: Capital social | B23: 1389 | C23: 1381 | D23: 1371 | E23: =IFERROR(C23/B23-1,"-") -> -0.0057595392 | F23: =IFERROR(D23/C23-1,"-") -> -0.0072411296
A24: Primes d'emission et d'apport | B24: 3706 | C24: 3482 | D24: 3192 | E24: =IFERROR(C24/B24-1,"-") -> -0.060442526 | F24: =IFERROR(D24/C24-1,"-") -> -0.083285468
A25: Reserves et report a nouveau | B25: 3085 | C25: 3928 | D25: 5541 | E25: =IFERROR(C25/B25-1,"-") -> 0.2732577 | F25: =IFERROR(D25/C25-1,"-") -> 0.41064155
A26: Resultat net de l'exercice | B26: 1547 | C26: 1663 | D26: 1671 | E26: =IFERROR(C26/B26-1,"-") -> 0.07498384 | F26: =IFERROR(D26/C26-1,"-") -> 0.0048105833
A27: Capitaux propres part du Groupe | B27: 9727 | C27: 10454 | D27: 11775 | E27: =IFERROR(C27/B27-1,"-") -> 0.074740413 | F27: =IFERROR(D27/C27-1,"-") -> 0.12636311
A28: Interets minoritaires | B28: 16 | C28: 19 | D28: 22 | E28: =IFERROR(C28/B28-1,"-") -> 0.1875 | F28: =IFERROR(D28/C28-1,"-") -> 0.15789474
A29: TOTAL CAPITAUX PROPRES | B29: 9743 | C29: 10473 | D29: 11797 | E29: =IFERROR(C29/B29-1,"-") -> 0.074925588 | F29: =IFERROR(D29/C29-1,"-") -> 0.12642032
A30: Dettes financieres long terme | B30: 5655 | C30: 5071 | D30: 4281 | E30: =IFERROR(C30/B30-1,"-") -> -0.10327144 | F30: =IFERROR(D30/C30-1,"-") -> -0.15578781
A31: Impots differes passifs | B31: 308 | C31: 275 | D31: 267 | E31: =IFERROR(C31/B31-1,"-") -> -0.10714286 | F31: =IFERROR(D31/C31-1,"-") -> -0.029090909
A32: Provisions pour retraites | B32: 365 | C32: 331 | D32: 309 | E32: =IFERROR(C32/B32-1,"-") -> -0.093150685 | F32: =IFERROR(D32/C32-1,"-") -> -0.066465257
A33: Provisions non courantes | B33: 339 | C33: 327 | D33: 274 | E33: =IFERROR(C33/B33-1,"-") -> -0.03539823 | F33: =IFERROR(D33/C33-1,"-") -> -0.16207951
A34: Dettes de loyers non courantes | B34: 533 | C34: 598 | D34: 671 | E34: =IFERROR(C34/B34-1,"-") -> 0.12195122 | F34: =IFERROR(D34/C34-1,"-") -> 0.12207358
... A45: TOTAL CAPITAUX PROPRES ET PASSIF | B45: 25479 | C45: 24700 | D45: 25660 | E45: =IFERROR(C45/B45-1,"-") -> -0.030574198 | F45: =IFERROR(D45/C45-1,"-") -> 0.038866397
B47: =B20-B45 -> 0 | C47: =C20-C45 -> 0 | D47: =D20-D45 -> 0
A49: Source : Rapports annuels consolides Capgemini SE (normes IFRS), investors.capgemini.com - Etats consolides de la situation financiere et Comptes de resultat consolides, exercices clos au 31/12.

Sheet Flux de tresorerie
A1: TABLEAU DES FLUX DE TRESORERIE CONSOLIDES (SYNTHESE)
A2: En millions d'euros
A4: Rubrique | B4: 2022 | C4: 2023 | D4: 2024
A5: Resultat net | B5: 1550 | C5: 1668 | D5: 1677
A6: Dotations aux amortissements et depreciations | B6: 719 | C6: 700 | D6: 683
A7: FLUX DE TRESORERIE LIES A L'ACTIVITE | B7: 2517 | C7: 2525 | D7: 2526
A8: FLUX DE TRESORERIE LIES AUX OPERATIONS D'INVESTISSEMENT | B8: -659 | C8: -383 | D8: -1337
A9: dont acquisitions d'immobilisations (nettes) | B9: -283 | C9: -254 | D9: -310
A10: dont acquisitions d'entreprises nettes de tresorerie | B10: -204 | C10: -343 | D10: -827
A11: FLUX DE TRESORERIE LIES AUX OPERATIONS DE FINANCEMENT | B11: -1124 | C11: -2305 | D11: -2016
A12: dont dividendes verses | B12: -409 | C12: -559 | D12: -584
A13: VARIATION DE LA TRESORERIE | B13: 734 | C13: -163 | D13: -827
A14: Endettement net en fin d'exercice (Note 22) | B14: 2566 | C14: 2047 | D14: 2107
A16: EBITDA reconstitue (Marge operationnelle + Dotations amort.) | B16: ='Compte de resultat'!B10+B6 -> 3586 | C16: ='Compte de resultat'!C10+C6 -> 3691 | D16: ='Compte de resultat'!D10+D6 -> 3617

Sheet Ratios financiers
A1: RATIOS FINANCIERS
A2: Calcules a partir des feuilles Compte de resultat, Bilan et Flux de tresorerie
A4: Ratio | B4: 2022 | C4: 2023 | D4: 2024 | E4: Mode de calcul
A5: 1. RENTABILITE
A6: Marge operationnelle | B6: ='Compte de resultat'!B10/'Compte de resultat'!B5 -> 0.13034781 | C6: ='Compte de resultat'!C10/'Compte de resultat'!C5 -> 0.13280348 | D6: ='Compte de resultat'!D10/'Compte de resultat'!D5 -> 0.13278421 | E6: Marge operationnelle / Chiffre d'affaires
A7: Marge nette | B7: ='Compte de resultat'!B16/'Compte de resultat'!B5 -> 0.070470561 | C7: ='Compte de resultat'!C16/'Compte de resultat'!C5 -> 0.074060918 | D7: ='Compte de resultat'!D16/'Compte de resultat'!D5 -> 0.07589609 | E7: Resultat net / Chiffre d'affaires
A8: ROE (rentabilite des capitaux propres, par Groupe) | B8: ='Compte de resultat'!B17/Bilan!B27 -> 0.15904184 | C8: ='Compte de resultat'!C17/Bilan!C27 -> 0.15907786 | D8: ='Compte de resultat'!D17/Bilan!D27 -> 0.14191083 | E8: Resultat net part Groupe / Capitaux propres part Groupe (fin d'exercice)
A9: ROA (rentabilite des actifs) | B9: ='Compte de resultat'!B16/Bilan!B20 -> 0.060834413 | C9: ='Compte de resultat'!C16/Bilan!C20 -> 0.067530364 | D9: ='Compte de resultat'!D16/Bilan!D20 -> 0.065354638 | E9: Resultat net / Total actif (fin d'exercice)
A11: 2. STRUCTURE FINANCIERE ET SOLVABILITE
A12: Autonomie financiere (capitaux propres / total bilan) | B12: =Bilan!B29/Bilan!B20 -> 0.38239334 | C12: =Bilan!C29/Bilan!C20 -> 0.4240081 | D12: =Bilan!D29/Bilan!D20 -> 0.45974279 | E12: Total capitaux propres / Total actif
A13: Gearing (endettement net / capitaux propres) | B13: ='Flux de tresorerie'!B14/Bilan!B29 -> 0.26336857 | C13: ='Flux de tresorerie'!C14/Bilan!C29 -> 0.19545498 | D13: ='Flux de tresorerie'!D14/Bilan!D29 -> 0.17860473 | E13: Endettement net / Total capitaux propres
A14: Endettement net / EBITDA | B14: ='Flux de tresorerie'!B14/'Flux de tresorerie'!B16 -> 0.71556051 | C14: ='Flux de tresorerie'!C14/'Flux de tresorerie'!C16 -> 0.55459225 | D14: ='Flux de tresorerie'!D14/'Flux de tresorerie'!D16 -> 0.58252696 | E14: Endettement net / EBITDA reconstitue
A15: Endettement net (M EUR) | B15: ='Flux de tresorerie'!B14 -> 2566 | C15: ='Flux de tresorerie'!C14 -> 2047 | D15: ='Flux de tresorerie'!D14 -> 2107 | E15: Rappel - Note 22 des rapports annuels
A17: 3. LIQUIDITE
A18: Ratio de liquidite generale (actif courant / passif courant) | B18: =Bilan!B19/Bilan!B44 -> 1.2823311 | C18: =Bilan!C19/Bilan!C44 -> 1.3441854 | D18: =Bilan!D19/Bilan!D44 -> 1.2074199 | E18: Total actif courant / Total passif courant
A19: Fonds de roulement net (M EUR) | B19: =Bilan!B19-Bilan!B44 -> 2277 | C19: =Bilan!C19-Bilan!C44 -> 2495 | D19: =Bilan!D19-Bilan!D44 -> 1599 | E19: Actif courant - Passif courant
A21: 4. GESTION / EFFICACITE OPERATIONNELLE
A22: Delai de recouvrement clients - DSO (jours) | B22: =Bilan!B7/'Compte de resultat'!B5*365 -> 14.53694 | C22: =Bilan!C7/'Compte de resultat'!C5*365 -> 12.770624 | D22: =Bilan!D7/'Compte de resultat'!D5*365 -> 12.471714 | E22: Creances clients / Chiffre d'affaires x 365
A23: Delai de paiement fournisseurs - DPO indicatif (jours) | B23: =Bilan!B38/'Compte de resultat'!B5*365 -> 78.808138 | C23: =Bilan!C38/'Compte de resultat'!C5*365 -> 74.030726 | D23: =Bilan!D38/'Compte de resultat'!D5*365 -> 77.522855 | E23: Dettes fournisseurs / Chiffre d'affaires x 365 (proxy, faute de detail achats)
A25: 5. CROISSANCE
A26: Croissance du chiffre d'affaires | B26: ="-" -> - | C26: ='Compte de resultat'!C5/'Compte de resultat'!B5-1 -> 0.023959991 | D26: ='Compte de resultat'!D5/'Compte de resultat'!C5-1 -> -0.018914839 | E26: Variation annuelle du CA
A27: TCAM du CA 2022-2024 (2 ans) | B27: =('Compte de resultat'!D5/'Compte de resultat'!B5)^(1/2)-1 -> 0.0022933466 | E27: Taux de croissance annuel moyen sur la periode
A32: Ces ratios sont calcules automatiquement par formules a partir des feuilles Compte de resultat, Bilan et Flux de tresorerie : toute correction sur ces feuilles se repercute ici.
